{
    "typeName": "ContentType",
    "typeVariableName": "contentType",
    "scriptPath": "C://component//lib//contentType.js",
    "prototypeScriptPath": "C://component//lib//contentType.prototype.js",
    "factoryScriptPath": "C://component//lib//factory//generated//contenttype//contenttype.factory.js",
    "bindingName": "Default",
    "bindingFilePath": "C://component//lib//factory//generated//contenttype//contenttype.factory.container.default.binding.json",
    "isSingleton": null,
    "CtorParameters": {
        "name": null
    }
}