{
    "typeName": "SenderAddress",
    "typeVariableName": "senderAddress",
    "scriptPath": "D://component//lib//senderaddress.js",
    "bindingName": "ServerMessageBusSpec",
    "bindingFilePath": "D://component//lib//factory//generated//senderaddress//senderaddress.factory.container.servermessagebusspec.binding.json",
    "defaultBindingName": "Default",
    "defaultBindingFilePath": "D://component//lib//factory//generated//senderaddress//senderaddress.factory.container.default.binding.json",
    "isBindingSingleton": false,
    "isSingleton": false,
    "ctorParameters": {
        "senderHost": null,
        "senderPort": null
    }
}